{"stat.useItem.minecraft.golden_apple":3,"stat.flyOneCm":43315,"stat.useItem.minecraft.ender_pearl":2,"stat.walkOneCm":46565,"stat.drop":5,"stat.jump":41,"stat.playerKills":3,"stat.playOneMinute":5326,"achievement.openInventory":17,"stat.fallOneCm":1885,"stat.leaveGame":1,"stat.damageTaken":1972,"stat.damageDealt":22456,"stat.timeSinceDeath":5326,"stat.sprintOneCm":34194,"achievement.exploreAllBiomes":{"value":0,"progress":["Plains"]},"stat.useItem.minecraft.diamond_sword":174,"stat.useItem.minecraft.potion":16}