{"stat.walkOneCm":1277067,"stat.playerKills":7,"stat.leaveGame":7,"stat.useItem.minecraft.glass_bottle":1,"stat.useItem.minecraft.diamond_sword":1966,"stat.useItem.minecraft.potion":267,"stat.noteblockPlayed":20,"stat.jump":1145,"stat.swimOneCm":250,"stat.fallOneCm":53166,"stat.crouchOneCm":459,"stat.sprintOneCm":635394,"achievement.exploreAllBiomes":{"value":0,"progress":["Plains"]},"achievement.openInventory":102,"stat.damageTaken":31141,"stat.useItem.minecraft.golden_apple":7,"stat.flyOneCm":724783,"stat.deaths":24,"stat.useItem.minecraft.ender_pearl":24,"stat.drop":71,"stat.playOneMinute":140846,"stat.useItem.minecraft.cooked_beef":15,"stat.damageDealt":252289,"stat.timeSinceDeath":7780,"stat.diveOneCm":1434}