{"stat.chestOpened":1,"stat.useItem.minecraft.bow":11,"stat.walkOneCm":1290413,"stat.playerKills":13,"stat.useItem.minecraft.iron_axe":17,"stat.leaveGame":125,"stat.useItem.minecraft.cobblestone":209,"stat.useItem.minecraft.diamond_sword":1008,"stat.useItem.minecraft.potion":78,"stat.jump":5003,"stat.swimOneCm":819,"stat.fallOneCm":242021,"stat.crouchOneCm":2094,"stat.useItem.minecraft.dirt":1,"stat.sprintOneCm":766189,"achievement.exploreAllBiomes":{"value":0,"progress":["Plains"]},"stat.useItem.minecraft.netherrack":1,"achievement.openInventory":72,"stat.damageTaken":10009,"stat.useItem.minecraft.golden_apple":6,"stat.flyOneCm":1855793,"stat.deaths":17,"stat.useItem.minecraft.ender_pearl":16,"stat.drop":41,"stat.playOneMinute":672741,"stat.useItem.minecraft.wooden_sword":62,"stat.useItem.minecraft.cooked_beef":6,"stat.damageDealt":132652,"stat.timeSinceDeath":375314}